mspypeline/__init__.py
mspypeline/__main__.py
mspypeline/version.py
mspypeline/config/ms_analysis_adjustable_options.yml
mspypeline/config/ms_analysis_default.yml
mspypeline/config/go_terms/GO_APOPTOTIC_SIGNALING_PATHWAY.txt
mspypeline/config/go_terms/GO_CYTOKINE_PRODUCTION.txt
mspypeline/config/go_terms/GO_EPITHELIAL_TO_MESENCHYMAL_TRANSITION.txt
mspypeline/config/go_terms/GO_EXTRACELLULAR_MATRIX.txt
mspypeline/config/go_terms/GO_GROWTH.txt
mspypeline/config/go_terms/GO_IMMUNE_RECEPTOR_ACTIVITY.txt
mspypeline/config/go_terms/GO_INFLAMMATORY_RESPONSE.txt
mspypeline/config/go_terms/GO_NEGATIVE_REGULATION_OF_INFLAMMATORY_RESPONSE.txt
mspypeline/config/go_terms/GO_NUCLEUS_LOCALIZATION.txt
mspypeline/config/go_terms/GO_PLASMA_MEMBRANE_REGION.txt
mspypeline/config/go_terms/GO_POSITIVE_REGULATION_OF_TRANSFORMING_GROWTH_FACTOR_BETA_PRODUCTION.txt
mspypeline/config/go_terms/GO_POSITIVE_REGULATION_OF_WNT_SIGNALING_PATHWAY.txt
mspypeline/config/go_terms/GO_REGENERATION.txt
mspypeline/config/pathways/BIOCARTA_EGF_PATHWAY.txt
mspypeline/config/pathways/BIOCARTA_EPO_PATHWAY.txt
mspypeline/config/pathways/BIOCARTA_TGFB_PATHWAY.txt
mspypeline/config/pathways/HALLMARK_APOPTOSIS.txt
mspypeline/config/pathways/HALLMARK_BILE_ACID_METABOLISM.txt
mspypeline/config/pathways/HALLMARK_CHOLESTEROL_HOMEOSTASIS.txt
mspypeline/config/pathways/HALLMARK_DNA_REPAIR.txt
mspypeline/config/pathways/HALLMARK_FATTY_ACID_METABOLISM.txt
mspypeline/config/pathways/HALLMARK_IL2_STAT5_SIGNALING.txt
mspypeline/config/pathways/HALLMARK_IL6_JAK_STAT3_SIGNALING.txt
mspypeline/config/pathways/HALLMARK_INFLAMMATORY_RESPONSE.txt
mspypeline/config/pathways/HALLMARK_INTERFERON_ALPHA_RESPONSE.txt
mspypeline/config/pathways/HALLMARK_INTERFERON_GAMMA_RESPONSE.txt
mspypeline/config/pathways/HALLMARK_REACTIVE_OXYGEN_SPECIES_PATHWAY.txt
mspypeline/core/MSPInitializer.py
mspypeline/core/MSPypeline.py
mspypeline/core/__init__.py
mspypeline/core/MSPPlots/BasePlotter.py
mspypeline/core/MSPPlots/MaxQuantPlotter.py
mspypeline-0.11.0.dist-info/LICENSE.txt
mspypeline-0.11.0.dist-info/METADATA
mspypeline-0.11.0.dist-info/WHEEL
mspypeline-0.11.0.dist-info/top_level.txt
mspypeline-0.11.0.dist-info/RECORD
