Metadata-Version: 2.1
Name: mspypeline
Version: 0.11.0
Summary: Package to analyze Mass Spec Data
Home-page: UNKNOWN
License: UNKNOWN
Project-URL: Documentation, https://mspypeline.readthedocs.io/en/stable/
Project-URL: Source, https://github.com/siheming/mspypeline
Project-URL: Bug Tracker, https://github.com/siheming/mspypeline/issues
Platform: UNKNOWN
Classifier: Programming Language :: Python :: 3
Classifier: License :: OSI Approved :: MIT License
Classifier: Operating System :: OS Independent
Requires-Dist: numpy (>=1.17.4)
Requires-Dist: pandas (>=1.0.0)
Requires-Dist: scipy (>=1.3.1)
Requires-Dist: rpy2 (>=3.4.2)
Requires-Dist: tzlocal (>=2.0.0)
Requires-Dist: ruamel-yaml (>=0.15.46)
Requires-Dist: matplotlib (>=3.1.1)
Requires-Dist: matplotlib-venn (>=0.11.5)
Requires-Dist: adjusttext (>=0.7.3)
Requires-Dist: scikit-learn (>=0.22.1)
